<annotation>
	<folder></folder>
	<filename>14DLPPEQDU39_jpg.rf.d5047f206f360fe230e06d88935b3c38.jpg</filename>
	<path>14DLPPEQDU39_jpg.rf.d5047f206f360fe230e06d88935b3c38.jpg</path>
	<source>
		<database>roboflow.com</database>
	</source>
	<size>
		<width>640</width>
		<height>640</height>
		<depth>3</depth>
	</size>
	<segmented>0</segmented>
	<object>
		<name>heavyweapon</name>
		<pose>Unspecified</pose>
		<truncated>0</truncated>
		<difficult>0</difficult>
		<occluded>0</occluded>
		<bndbox>
			<xmin>1</xmin>
			<xmax>625</xmax>
			<ymin>66</ymin>
			<ymax>421</ymax>
		</bndbox>
	</object>
</annotation>
