<annotation>
	<folder></folder>
	<filename>5DVGQJMSU85O_jpg.rf.bfc95afb0ee2ec8f563cc6d3aafdff62.jpg</filename>
	<path>5DVGQJMSU85O_jpg.rf.bfc95afb0ee2ec8f563cc6d3aafdff62.jpg</path>
	<source>
		<database>roboflow.com</database>
	</source>
	<size>
		<width>640</width>
		<height>640</height>
		<depth>3</depth>
	</size>
	<segmented>0</segmented>
	<object>
		<name>heavyweapon</name>
		<pose>Unspecified</pose>
		<truncated>0</truncated>
		<difficult>0</difficult>
		<occluded>0</occluded>
		<bndbox>
			<xmin>21</xmin>
			<xmax>580</xmax>
			<ymin>378</ymin>
			<ymax>461</ymax>
		</bndbox>
	</object>
	<object>
		<name>heavyweapon</name>
		<pose>Unspecified</pose>
		<truncated>0</truncated>
		<difficult>0</difficult>
		<occluded>0</occluded>
		<bndbox>
			<xmin>22</xmin>
			<xmax>590</xmax>
			<ymin>221</ymin>
			<ymax>287</ymax>
		</bndbox>
	</object>
	<object>
		<name>heavyweapon</name>
		<pose>Unspecified</pose>
		<truncated>0</truncated>
		<difficult>0</difficult>
		<occluded>0</occluded>
		<bndbox>
			<xmin>19</xmin>
			<xmax>593</xmax>
			<ymin>57</ymin>
			<ymax>126</ymax>
		</bndbox>
	</object>
	<object>
		<name>heavyweapon</name>
		<pose>Unspecified</pose>
		<truncated>0</truncated>
		<difficult>0</difficult>
		<occluded>0</occluded>
		<bndbox>
			<xmin>31</xmin>
			<xmax>584</xmax>
			<ymin>107</ymin>
			<ymax>175</ymax>
		</bndbox>
	</object>
	<object>
		<name>heavyweapon</name>
		<pose>Unspecified</pose>
		<truncated>0</truncated>
		<difficult>0</difficult>
		<occluded>0</occluded>
		<bndbox>
			<xmin>27</xmin>
			<xmax>595</xmax>
			<ymin>262</ymin>
			<ymax>342</ymax>
		</bndbox>
	</object>
	<object>
		<name>heavyweapon</name>
		<pose>Unspecified</pose>
		<truncated>0</truncated>
		<difficult>0</difficult>
		<occluded>0</occluded>
		<bndbox>
			<xmin>34</xmin>
			<xmax>592</xmax>
			<ymin>312</ymin>
			<ymax>397</ymax>
		</bndbox>
	</object>
	<object>
		<name>heavyweapon</name>
		<pose>Unspecified</pose>
		<truncated>0</truncated>
		<difficult>0</difficult>
		<occluded>0</occluded>
		<bndbox>
			<xmin>32</xmin>
			<xmax>602</xmax>
			<ymin>159</ymin>
			<ymax>244</ymax>
		</bndbox>
	</object>
	<object>
		<name>heavyweapon</name>
		<pose>Unspecified</pose>
		<truncated>0</truncated>
		<difficult>0</difficult>
		<occluded>0</occluded>
		<bndbox>
			<xmin>45</xmin>
			<xmax>593</xmax>
			<ymin>446</ymin>
			<ymax>513</ymax>
		</bndbox>
	</object>
	<object>
		<name>heavyweapon</name>
		<pose>Unspecified</pose>
		<truncated>0</truncated>
		<difficult>0</difficult>
		<occluded>0</occluded>
		<bndbox>
			<xmin>45</xmin>
			<xmax>593</xmax>
			<ymin>495</ymin>
			<ymax>566</ymax>
		</bndbox>
	</object>
	<object>
		<name>heavyweapon</name>
		<pose>Unspecified</pose>
		<truncated>0</truncated>
		<difficult>0</difficult>
		<occluded>0</occluded>
		<bndbox>
			<xmin>58</xmin>
			<xmax>593</xmax>
			<ymin>551</ymin>
			<ymax>641</ymax>
		</bndbox>
	</object>
	<object>
		<name>heavyweapon</name>
		<pose>Unspecified</pose>
		<truncated>0</truncated>
		<difficult>0</difficult>
		<occluded>0</occluded>
		<bndbox>
			<xmin>49</xmin>
			<xmax>613</xmax>
			<ymin>12</ymin>
			<ymax>77</ymax>
		</bndbox>
	</object>
</annotation>
