<annotation>
	<folder></folder>
	<filename>9e9875ed-6641-4cbb-aeed-a84c9f2a4689_jpg.rf.ae42c6e6cb3a4dbe54d7753b264d9be3.jpg</filename>
	<path>9e9875ed-6641-4cbb-aeed-a84c9f2a4689_jpg.rf.ae42c6e6cb3a4dbe54d7753b264d9be3.jpg</path>
	<source>
		<database>roboflow.com</database>
	</source>
	<size>
		<width>640</width>
		<height>640</height>
		<depth>3</depth>
	</size>
	<segmented>0</segmented>
	<object>
		<name>mace</name>
		<pose>Unspecified</pose>
		<truncated>0</truncated>
		<difficult>0</difficult>
		<occluded>0</occluded>
		<bndbox>
			<xmin>48</xmin>
			<xmax>591</xmax>
			<ymin>64</ymin>
			<ymax>571</ymax>
		</bndbox>
	</object>
</annotation>
