<annotation>
	<folder></folder>
	<filename>9IRWIMIZ01WE_jpg.rf.3b090c8690f0ec4c7d8aecf93a2c318c.jpg</filename>
	<path>9IRWIMIZ01WE_jpg.rf.3b090c8690f0ec4c7d8aecf93a2c318c.jpg</path>
	<source>
		<database>roboflow.com</database>
	</source>
	<size>
		<width>640</width>
		<height>640</height>
		<depth>3</depth>
	</size>
	<segmented>0</segmented>
	<object>
		<name>heavyweapon</name>
		<pose>Unspecified</pose>
		<truncated>0</truncated>
		<difficult>0</difficult>
		<occluded>0</occluded>
		<bndbox>
			<xmin>19</xmin>
			<xmax>624</xmax>
			<ymin>313</ymin>
			<ymax>508</ymax>
		</bndbox>
	</object>
</annotation>
