<annotation>
	<folder></folder>
	<filename>C4L56KE7AZL5_jpg.rf.dff2f80ddf7123a156cc6a2926f0c772.jpg</filename>
	<path>C4L56KE7AZL5_jpg.rf.dff2f80ddf7123a156cc6a2926f0c772.jpg</path>
	<source>
		<database>roboflow.com</database>
	</source>
	<size>
		<width>640</width>
		<height>640</height>
		<depth>3</depth>
	</size>
	<segmented>0</segmented>
	<object>
		<name>heavyweapon</name>
		<pose>Unspecified</pose>
		<truncated>0</truncated>
		<difficult>0</difficult>
		<occluded>0</occluded>
		<bndbox>
			<xmin>20</xmin>
			<xmax>390</xmax>
			<ymin>13</ymin>
			<ymax>551</ymax>
		</bndbox>
	</object>
	<object>
		<name>heavyweapon</name>
		<pose>Unspecified</pose>
		<truncated>0</truncated>
		<difficult>0</difficult>
		<occluded>0</occluded>
		<bndbox>
			<xmin>297</xmin>
			<xmax>607</xmax>
			<ymin>30</ymin>
			<ymax>625</ymax>
		</bndbox>
	</object>
</annotation>
