<annotation>
	<folder></folder>
	<filename>Linggis-42-_jpg.rf.11db9dce1708d42e2c56c91e7d5d1c1e.jpg</filename>
	<path>Linggis-42-_jpg.rf.11db9dce1708d42e2c56c91e7d5d1c1e.jpg</path>
	<source>
		<database>roboflow.com</database>
	</source>
	<size>
		<width>640</width>
		<height>640</height>
		<depth>3</depth>
	</size>
	<segmented>0</segmented>
	<object>
		<name>Linggis</name>
		<pose>Unspecified</pose>
		<truncated>0</truncated>
		<difficult>0</difficult>
		<occluded>0</occluded>
		<bndbox>
			<xmin>53</xmin>
			<xmax>583</xmax>
			<ymin>135</ymin>
			<ymax>515</ymax>
		</bndbox>
	</object>
</annotation>
