<annotation>
	<folder></folder>
	<filename>SMG_73_jpeg_jpg.rf.7a21555c8304a84c41e14f0c63fe9284.jpg</filename>
	<path>SMG_73_jpeg_jpg.rf.7a21555c8304a84c41e14f0c63fe9284.jpg</path>
	<source>
		<database>roboflow.com</database>
	</source>
	<size>
		<width>640</width>
		<height>640</height>
		<depth>3</depth>
	</size>
	<segmented>0</segmented>
	<object>
		<name>smg</name>
		<pose>Unspecified</pose>
		<truncated>0</truncated>
		<difficult>0</difficult>
		<occluded>0</occluded>
		<bndbox>
			<xmin>153</xmin>
			<xmax>539</xmax>
			<ymin>14</ymin>
			<ymax>641</ymax>
		</bndbox>
	</object>
</annotation>
