<annotation>
	<folder></folder>
	<filename>sword-fighting-games-intro_jpg.rf.605b848693e15438a2b09b4bac6e67f4.jpg</filename>
	<path>sword-fighting-games-intro_jpg.rf.605b848693e15438a2b09b4bac6e67f4.jpg</path>
	<source>
		<database>roboflow.com</database>
	</source>
	<size>
		<width>640</width>
		<height>640</height>
		<depth>3</depth>
	</size>
	<segmented>0</segmented>
	<object>
		<name>katana</name>
		<pose>Unspecified</pose>
		<truncated>0</truncated>
		<difficult>0</difficult>
		<occluded>0</occluded>
		<bndbox>
			<xmin>5</xmin>
			<xmax>493</xmax>
			<ymin>245</ymin>
			<ymax>419</ymax>
		</bndbox>
	</object>
	<object>
		<name>sword</name>
		<pose>Unspecified</pose>
		<truncated>0</truncated>
		<difficult>0</difficult>
		<occluded>0</occluded>
		<bndbox>
			<xmin>29</xmin>
			<xmax>183</xmax>
			<ymin>98</ymin>
			<ymax>368</ymax>
		</bndbox>
	</object>
</annotation>
