<annotation>
	<folder></folder>
	<filename>W08VL6HJXQVL_jpg.rf.e5e23cb12c8710db2e15bdaca421fdf4.jpg</filename>
	<path>W08VL6HJXQVL_jpg.rf.e5e23cb12c8710db2e15bdaca421fdf4.jpg</path>
	<source>
		<database>roboflow.com</database>
	</source>
	<size>
		<width>640</width>
		<height>640</height>
		<depth>3</depth>
	</size>
	<segmented>0</segmented>
	<object>
		<name>heavyweapon</name>
		<pose>Unspecified</pose>
		<truncated>0</truncated>
		<difficult>0</difficult>
		<occluded>0</occluded>
		<bndbox>
			<xmin>1</xmin>
			<xmax>358</xmax>
			<ymin>16</ymin>
			<ymax>462</ymax>
		</bndbox>
	</object>
	<object>
		<name>heavyweapon</name>
		<pose>Unspecified</pose>
		<truncated>0</truncated>
		<difficult>0</difficult>
		<occluded>0</occluded>
		<bndbox>
			<xmin>109</xmin>
			<xmax>481</xmax>
			<ymin>20</ymin>
			<ymax>460</ymax>
		</bndbox>
	</object>
	<object>
		<name>heavyweapon</name>
		<pose>Unspecified</pose>
		<truncated>0</truncated>
		<difficult>0</difficult>
		<occluded>0</occluded>
		<bndbox>
			<xmin>217</xmin>
			<xmax>591</xmax>
			<ymin>42</ymin>
			<ymax>452</ymax>
		</bndbox>
	</object>
</annotation>
